dwa/__init__.py
dwa/core.py
dwa/handlers.py
dwa/utils.py
dwa/workers.py
dwa/__metadata__/DISCLIAIMER.md
dwa/__metadata__/LICENSE
dwa/__metadata__/README.md
dwa/__metadata__/__init__.py
dwa/__metadata__/requirements.txt
dwa/example/README.md
dwa/example/app.py
dwa/example/cookie_secret.txt
dwa/example/test.py
dwa/example/common/api_utils.py
dwa/example/db/db.db
dwa/example/jobs/__init__.py
dwa/example/jobs/shop.py
dwa/example/pages/__init__.py
dwa/example/pages/root.py
dwa/example/pages/shop.py
dwa/example/root/index.html
dwa/example/root/common/api_utils.py
dwa/example/root/css/style.css
dwa/example/root/js/script.js
dwa/example/root/src/index.html
dwa/example/shop/admin_api.py
dwa/example/shop/index.html
dwa/example/shop/shop_api.py
dwa/example/shop/shop_utils.py
dwa/example/shop/template.html
dwa/example/shop/common/api_utils.py
dwa/example/shop/css/min/index.css
dwa/example/shop/css/min/style.css
dwa/example/shop/css/src/index.css
dwa/example/shop/css/src/style.css
dwa/example/shop/js/min/admin.js
dwa/example/shop/js/min/index.js
dwa/example/shop/js/min/script.js
dwa/example/shop/js/src/admin.js
dwa/example/shop/js/src/index.js
dwa/example/shop/js/src/script.js
dwa/example/shop/src/index.html
dwa/example/shop/src/template.html
dwa-0.0.43.dist-info/METADATA
dwa-0.0.43.dist-info/WHEEL
dwa-0.0.43.dist-info/top_level.txt
dwa-0.0.43.dist-info/RECORD
